playmedia/__init__.py
playmedia/multiple_files.py
playmedia/single_file.py
playmedia-1.0.0.dist-info/LICENSE
playmedia-1.0.0.dist-info/METADATA
playmedia-1.0.0.dist-info/WHEEL
playmedia-1.0.0.dist-info/top_level.txt
playmedia-1.0.0.dist-info/RECORD
