Metadata-Version: 2.1
Name: playmedia
Version: 1.0.0
Summary: A python package to play and control media files.
Home-page: https://github.com/satvikVirmani/playmedia
Author: Satvik Virmani
Author-email: virmanisatvik01@gmail.com
License: MIT License
Download-URL: https://github.com/satvikvirmani/playmedia/releases
Project-URL: Bug Tracker, https://github.com/satvikVirmani/playmedia/issues
Platform: UNKNOWN
Classifier: Programming Language :: Python :: 3
Classifier: License :: OSI Approved :: MIT License
Classifier: Operating System :: OS Independent
Requires-Python: >=3.0
License-File: LICENSE
Requires-Dist: pretty-errors
Requires-Dist: python-vlc
